stix_shifter_threatbus/__init__.py
stix_shifter_threatbus/message_mapping.py
stix_shifter_threatbus/shifter.py
stix_shifter_threatbus/test_message_mapping.py
stix_shifter_threatbus-2022.5.16.dist-info/METADATA
stix_shifter_threatbus-2022.5.16.dist-info/WHEEL
stix_shifter_threatbus-2022.5.16.dist-info/entry_points.txt
stix_shifter_threatbus-2022.5.16.dist-info/top_level.txt
stix_shifter_threatbus-2022.5.16.dist-info/RECORD
