Metadata-Version: 2.1
Name: stix-shifter-threatbus
Version: 2022.5.16
Summary: Bridges the gap between Threat Bus and STIX-Shifter
Home-page: https://github.com/tenzir/threatbus
Author: Tenzir
Author-email: engineering@tenzir.com
License: BSD 3-clause
Keywords: open source,threatbus,Threat Bus,threat intelligence,TI,TI dissemination
Platform: UNKNOWN
Classifier: Development Status :: 3 - Alpha
Classifier: License :: OSI Approved :: BSD License
Classifier: Operating System :: MacOS :: MacOS X
Classifier: Operating System :: POSIX :: Linux
Classifier: Topic :: Scientific/Engineering :: Information Analysis
Classifier: Topic :: Scientific/Engineering :: Interface Engine/Protocol Translator
Classifier: Topic :: Security
Classifier: Topic :: Software Development :: Object Brokering
Classifier: Topic :: System :: Distributed Computing
Requires-Python: >=3.7
Requires-Dist: black (>=19.10b)
Requires-Dist: dynaconf (!=3.1.8,>=3.1.4)
Requires-Dist: python-dateutil
Requires-Dist: pyzmq (>=19)
Requires-Dist: stix2 (>=3.0)
Requires-Dist: stix-shifter (>=3.4.2)
Requires-Dist: stix-shifter-utils (>=3.4.2)
Requires-Dist: threatbus (>=2022.5.16)
